LICENSE.txt
README.md
setup.py
winevt_ng/__init__.py
winevt_ng/_winevt_ng.pyd
winevt_ng/settings.py
winevt_ng/winevt_build.py
winevt_ng.egg-info/PKG-INFO
winevt_ng.egg-info/SOURCES.txt
winevt_ng.egg-info/dependency_links.txt
winevt_ng.egg-info/requires.txt
winevt_ng.egg-info/top_level.txt
winevt_ng/EventLog/Bookmark.py
winevt_ng/EventLog/Event.py
winevt_ng/EventLog/Query.py
winevt_ng/EventLog/Session.py
winevt_ng/EventLog/Subscribe.py
winevt_ng/EventLog/__init__.py