Metadata-Version: 2.1
Name: winevt-ng
Version: 0.1.0
Summary: Script to programmatically interface with Windows Events.
Home-page: https://github.com/schorschii/winevt_ng
License: MIT
Keywords: windows event log evt evtx
Classifier: Development Status :: 5 - Production/Stable
Classifier: Intended Audience :: End Users/Desktop
Classifier: License :: OSI Approved :: MIT License
Classifier: Programming Language :: Python :: 3
Classifier: Operating System :: Microsoft :: Windows
Classifier: Environment :: Console
Provides-Extra: dev
License-File: LICENSE.txt
